chainecho/__init__.py
chainecho/main.py
chainecho-1.0.dist-info/licenses/LICENSE
chainecho-1.0.dist-info/METADATA
chainecho-1.0.dist-info/WHEEL
chainecho-1.0.dist-info/top_level.txt
chainecho-1.0.dist-info/RECORD
